rundec.py
_rundec.cpython-310-aarch64-linux-gnu.so
rundec.libs/libstdc++-1b614e01.so.6.0.32
rundec.libs/libgcc_s-7393e603.so.1
rundec-0.6.dist-info/RECORD
rundec-0.6.dist-info/METADATA
rundec-0.6.dist-info/WHEEL
rundec-0.6.dist-info/top_level.txt
rundec-0.6.dist-info/LICENSE
