Metadata-Version: 2.1
Name: rundec
Version: 0.6
Summary: A Python wrapper around the CRunDec package for the  running and decoupling of the strong coupling constant and quark masses
Home-page: https://github.com/DavidMStraub/rundec-python
Author: David M. Straub
Author-email: david.straub@tum.de
License: MIT
Platform: UNKNOWN
License-File: LICENSE
Provides-Extra: testing
Requires-Dist: pytest ; extra == 'testing'
